biased_memory_toolbox.py
biased_memory_toolbox-1.3.0.dist-info/COPYING
biased_memory_toolbox-1.3.0.dist-info/METADATA
biased_memory_toolbox-1.3.0.dist-info/WHEEL
biased_memory_toolbox-1.3.0.dist-info/top_level.txt
biased_memory_toolbox-1.3.0.dist-info/RECORD
