Metadata-Version: 2.1
Name: biased-memory-toolbox
Version: 1.3.0
Summary: Mixture modeling for working-memory experiments
Home-page: https://github.com/smathot/biased_memory_toolbox
Author: Sebastiaan Mathot
Author-email: s.mathot@cogsci.nl
License: GNU GPL Version 3
Platform: UNKNOWN
Classifier: Development Status :: 4 - Beta
Classifier: Intended Audience :: Science/Research
Classifier: Topic :: Scientific/Engineering
Classifier: License :: OSI Approved :: GNU General Public License v3 (GPLv3)
Classifier: Programming Language :: Python :: 3
Requires-Dist: scipy
Requires-Dist: numpy
